{
	"this_is_the_time_that_you": {
		"en": "This is the time that you",
		"pt": "Esta é a hora que você"
	},
	"ate": {
		"en": "ate",
		"pt": "comeu"
	},
	"can_drink_water": {
		"en": "can drink water",
		"pt": "pode beber água"
	},
	"will_be_hungry": {
		"en": "will be hungry",
		"pt": "irá ter fome"
	},
	"time_that_i_finished_eating": {
		"en": "Time that I finished eating",
		"pt": "Tempo em que terminei de comer"
	},
	"time_that_you_will_be_hungry": {
		"en": "Time that you will be hungry",
		"pt": "Horário em que você terá fome"
	},
	"raw_times, en - pt": "Raw times - Tempos brutos",
	"hours": {
		"en": "hours",
		"pt": "horas"
	},
	"minutes": {
		"en": "minutes",
		"pt": "minutos"
	},
	"showing_the_meal_times_below": {
		"en": "Showing the meal times below",
		"pt": "Mostrando os horários da refeição abaixo"
	},
	"play_alarm_sound_when_you_are_hungry": {
		"en": "Play alarm sound when you are hungry",
		"pt": "Tocar som de alarme quando você estiver com fome"
	},
	"times_taken_from_the_times_file": {
		"en": "Times taken from the times file",
		"pt": "Horários retirados do arquivo de horários"
	},
	"times_registered_into_the_times_file": {
		"en": "Times registered into the times file",
		"pt": "Horários registrados no arquivo de horários"
	}
}